LICENSE
scex_py/__init__.py
scex_py/api_handler.py
scex_py/constants.py
scex_py/input_xml/balloon_payment/final.xml
scex_py/input_xml/balloon_payment/regular.xml
scex_py/input_xml/equal_payment_loan.xml
scex_py/input_xml/multi_term_payment_loan.xml
scex_py/scex_client.py
scex_py/utils.py
scex_py-1.0.9.dist-info/LICENSE
scex_py-1.0.9.dist-info/WHEEL
scex_py-1.0.9.dist-info/METADATA
scex_py-1.0.9.dist-info/RECORD
