Metadata-Version: 2.1
Name: scex-py
Version: 1.0.9
Summary: 
Home-page: https://github.com/Lenders-Cooperative/scex_py
License: BSD-3-Clause
Author: Jatin Goel
Author-email: jatin.goel@thesummitgrp.com
Requires-Python: >=3.10.2,<4.0.0
Classifier: License :: OSI Approved :: BSD License
Classifier: Programming Language :: Python :: 3
Classifier: Programming Language :: Python :: 3.11
Requires-Dist: requests (>=2.28.1,<2.29.0)
Requires-Dist: xmltodict (>=0.12.0,<0.13.0)
